<item>
<title>[B][COLOR yellow]ATUALIZACAO: 31.05.2016[/B][/COLOR]</title>
<link>http://0.0.0.0:1234</link>
<thumbnail></thumbnail>
</item>
<item>
<title>[B][COLOR white]--------------------------------------------------[/B][/COLOR]</title>
<link>http://0.0.0.0:1234</link>
<thumbnail></thumbnail>
</item>
**************************************************
BENFICA TV 1
<item>
<title>[B][COLOR lawngreen]•[/B][/COLOR] PT: [B][COLOR white]BENFICA TV 1 [B][COLOR red](f4mTester)[/B][/COLOR]</title>
<link>plugin://plugin.video.f4mTester/?url=http://hyper.de1-eu.com:8000/live/samsam/samsam/2844.ts;streamtype=TSDOWNLOADER|User-Agent=Mozilla/5.0 (iPad; CPU OS 6_0 like Mac OS X) AppleWebKit/536.26 (KHTML, like Gecko) Version/6.0 Mobile/10A5376e Safari/8536.25</link>
<thumbnail>http://i.imgur.com/FXDakNf.png</thumbnail>
</item>
BENFICA TV 2
<item>
<title>[B][COLOR lawngreen]•[/B][/COLOR] PT: [B][COLOR white]BENFICA TV 2 [B][COLOR red](f4mTester)[/B][/COLOR]</title>
<link>plugin://plugin.video.f4mTester/?url=http://ptbrvirtual.no-ip.net:8000/live/brunosofiamagalhaez@gmail.com/z0LyEB0MvT/253.ts;streamtype=TSDOWNLOADER|User-Agent=Mozilla/5.0 (iPad; CPU OS 6_0 like Mac OS X) AppleWebKit/536.26 (KHTML, like Gecko) Version/6.0 Mobile/10A5376e Safari/8536.25</link>
<thumbnail>http://i.imgur.com/mCK5Jwz.png</thumbnail>
</item>
EUROSPORT 1
<item>
<title>[B][COLOR lawngreen]•[/B][/COLOR] PT: [B][COLOR white]EUROSPORT 1 [B][COLOR red](f4mTester)[/B][/COLOR]</title>
<link>plugin://plugin.video.f4mTester/?url=http://ptbrvirtual.no-ip.net:8000/live/brunosofiamagalhaez@gmail.com/z0LyEB0MvT/170.ts;streamtype=TSDOWNLOADER|User-Agent=Mozilla/5.0 (iPad; CPU OS 6_0 like Mac OS X) AppleWebKit/536.26 (KHTML, like Gecko) Version/6.0 Mobile/10A5376e Safari/8536.25</link>
<thumbnail>http://i.imgur.com/00mXlvU.png</thumbnail>
</item>
EUROSPORT 2
<item>
<title></title>
<link></link>
<thumbnail></thumbnail>
</item>
EUROSPORT 2 XTRA
<item>
<title>[B][COLOR lawngreen]•[/B][/COLOR] PT: [B][COLOR white]EUROSPORT 2 XTRA [B][COLOR red](f4mTester)[/B][/COLOR]</title>
<link>plugin://plugin.video.f4mTester/?url=http://ptbrvirtual.no-ip.net:8000/live/brunosofiamagalhaez@gmail.com/z0LyEB0MvT/634.ts;streamtype=TSDOWNLOADER|User-Agent=Mozilla/5.0 (iPad; CPU OS 6_0 like Mac OS X) AppleWebKit/536.26 (KHTML, like Gecko) Version/6.0 Mobile/10A5376e Safari/8536.25</link>
<thumbnail>http://i.imgur.com/0tybBJ0.jpg</thumbnail>
</item>
EUROSPORT NEWS
<item>
<title>[B][COLOR lawngreen]•[/B][/COLOR] PT: [B][COLOR white]EUROSPORT NEWS [B][COLOR red](f4mTester)[/B][/COLOR]</title>
<link>plugin://plugin.video.f4mTester/?url=http://ipsatpro.com:8000/live/persian.eagle/persian.eagle/922.ts;streamtype=TSDOWNLOADER|User-Agent=Mozilla/5.0 (iPad; CPU OS 6_0 like Mac OS X) AppleWebKit/536.26 (KHTML, like Gecko) Version/6.0 Mobile/10A5376e Safari/8536.25</link>
<thumbnail>http://i.imgur.com/r6gIP7Y.png</thumbnail>
</item>
MOTORS TV
<item>
<title></title>
<link></link>
<thumbnail></thumbnail>
</item>
MOTORVISION TV
<item>
<title>[B][COLOR lawngreen]•[/B][/COLOR] UK: [B][COLOR white]MOTORVISION TV [B][COLOR red](f4mTester)[/B][/COLOR]</title>
<link>plugin://plugin.video.f4mTester/?url=http://worldcs.info:8080/live/SUsojOyxUv/LR16au3pFJ/685.ts;streamtype=TSDOWNLOADER|User-Agent=Mozilla/5.0 (iPad; CPU OS 6_0 like Mac OS X) AppleWebKit/536.26 (KHTML, like Gecko) Version/6.0 Mobile/10A5376e Safari/8536.25</link>
<thumbnail>http://i.imgur.com/ixMRmkM.png</thumbnail>
</item>
PFC
<item>
<title></title>
<link></link>
<thumbnail></thumbnail>
</item>
SPORT TV 1
<item>
<title>[B][COLOR lawngreen]•[/B][/COLOR] PT: [B][COLOR white]SPORT TV 1 [B][COLOR red](f4mTester)[/B][/COLOR]</title>
<link>plugin://plugin.video.f4mTester/?url=http://cdn02.selling-team.net:8000/live/49JRfRYKfp/BIOFAEXP1607/6029.ts;streamtype=TSDOWNLOADER|User-Agent=Mozilla/5.0 (iPad; CPU OS 6_0 like Mac OS X) AppleWebKit/536.26 (KHTML, like Gecko) Version/6.0 Mobile/10A5376e Safari/8536.25</link>
<thumbnail>http://i.imgur.com/3rjsCFB.png</thumbnail>
</item>
SPORT TV 2
<item>
<title>[B][COLOR lawngreen]•[/B][/COLOR] PT: [B][COLOR white]SPORT TV 2 [B][COLOR red](f4mTester)[/B][/COLOR]</title>
<link>plugin://plugin.video.f4mTester/?url=http://ptbrvirtual.no-ip.net:8000/live/brunosofiamagalhaez@gmail.com/z0LyEB0MvT/29.ts;streamtype=TSDOWNLOADER|User-Agent=Mozilla/5.0 (iPad; CPU OS 6_0 like Mac OS X) AppleWebKit/536.26 (KHTML, like Gecko) Version/6.0 Mobile/10A5376e Safari/8536.25</link>
<thumbnail>http://i.imgur.com/fsgRDjH.png</thumbnail>
</item>
SPORT TV 3
<item>
<title>[B][COLOR lawngreen]•[/B][/COLOR] PT: [B][COLOR white]SPORT TV 3 [B][COLOR red](f4mTester)[/B][/COLOR]</title>
<link>plugin://plugin.video.f4mTester/?url=http://ptbrvirtual.no-ip.net:8000/live/brunosofiamagalhaez@gmail.com/z0LyEB0MvT/30.ts;streamtype=TSDOWNLOADER|User-Agent=Mozilla/5.0 (iPad; CPU OS 6_0 like Mac OS X) AppleWebKit/536.26 (KHTML, like Gecko) Version/6.0 Mobile/10A5376e Safari/8536.25</link>
<thumbnail>http://i.imgur.com/XvI6JNr.png</thumbnail>
</item>
SPORT TV 4
<item>
<title>[B][COLOR lawngreen]•[/B][/COLOR] PT: [B][COLOR white]SPORT TV 4 [B][COLOR red](f4mTester)[/B][/COLOR]</title>
<link>plugin://plugin.video.f4mTester/?url=http://89.114.56.194:8010/play/a03v;streamtype=TSDOWNLOADER|User-Agent=Mozilla/5.0 (iPad; CPU OS 6_0 like Mac OS X) AppleWebKit/536.26 (KHTML, like Gecko) Version/6.0 Mobile/10A5376e Safari/8536.25</link>
<thumbnail>http://i.imgur.com/IZCGvyl.png</thumbnail>
</item>
SPORT TV 5
<item>
<title>[B][COLOR lawngreen]•[/B][/COLOR] PT: [B][COLOR white]SPORT TV 5 [B][COLOR red](f4mTester)[/B][/COLOR]</title>
<link>plugin://plugin.video.f4mTester/?url=http://ptbrvirtual.no-ip.net:8000/live/brunosofiamagalhaez@gmail.com/z0LyEB0MvT/32.ts;streamtype=TSDOWNLOADER|User-Agent=Mozilla/5.0 (iPad; CPU OS 6_0 like Mac OS X) AppleWebKit/536.26 (KHTML, like Gecko) Version/6.0 Mobile/10A5376e Safari/8536.25</link>
<thumbnail>http://i.imgur.com/G8yH187.png</thumbnail>
</item>
SPORTING TV
<item>
<title>[B][COLOR lawngreen]•[/B][/COLOR] PT: [B][COLOR white]SPORTING TV [B][COLOR red](f4mTester)[/B][/COLOR]</title>
<link>plugin://plugin.video.f4mTester/?url=http://ptbrvirtual.no-ip.net:8000/live/brunosofiamagalhaez@gmail.com/z0LyEB0MvT/34.ts;streamtype=TSDOWNLOADER|User-Agent=Mozilla/5.0 (iPad; CPU OS 6_0 like Mac OS X) AppleWebKit/536.26 (KHTML, like Gecko) Version/6.0 Mobile/10A5376e Safari/8536.25</link>
<thumbnail>http://i.imgur.com/KTEBwY0.png</thumbnail>
</item>
