<item>
<title>[B][COLOR yellow]ATUALIZACAO: 28.05.2016[/B][/COLOR]</title>
<link>http://0.0.0.0:1234</link>
<thumbnail></thumbnail>
</item>
<item>
<title>[B][COLOR white]--------------------------------------------------[/B][/COLOR]</title>
<link>http://0.0.0.0:1234</link>
<thumbnail></thumbnail>
</item>
**************************************************
BABY TV
<item>
<title>[B][COLOR lawngreen]•[/B][/COLOR] PT: [B][COLOR white]BABY TV[B][COLOR royalblue] [SD] [B][COLOR red](f4mTester)[/B][/COLOR]</title>
<link>plugin://plugin.video.f4mTester/?url=http://89.114.56.194:8010/play/a03e;streamtype=TSDOWNLOADER|User-Agent=Mozilla/5.0 (iPad; CPU OS 6_0 like Mac OS X) AppleWebKit/536.26 (KHTML, like Gecko) Version/6.0 Mobile/10A5376e Safari/8536.25</link>
<thumbnail>http://i.imgur.com/xTAptxu.png</thumbnail>
</item>
CANAL PANDA
<item>
<title>[B][COLOR lawngreen]•[/B][/COLOR] PT: [B][COLOR white]CANAL PANDA[B][COLOR royalblue] [SD] [B][COLOR red](f4mTester)[/B][/COLOR]</title>
<link>plugin://plugin.video.f4mTester/?url=http://5.39.66.183:8000/live/bruno/bruno/489.ts;streamtype=TSDOWNLOADER|User-Agent=Mozilla/5.0 (iPad; CPU OS 6_0 like Mac OS X) AppleWebKit/536.26 (KHTML, like Gecko) Version/6.0 Mobile/10A5376e Safari/8536.25</link>
<thumbnail>http://i.imgur.com/zWiKosU.png</thumbnail>
</item>
CARTOON NETWORK
<item>
<title>[B][COLOR lawngreen]•[/B][/COLOR] PT: [B][COLOR white]CARTOON NETWORK[B][COLOR royalblue] [SD] [B][COLOR red](f4mTester)[/B][/COLOR]</title>
<link>plugin://plugin.video.f4mTester/?url=http://5.39.66.183:8000/live/bruno/bruno/813.ts;streamtype=TSDOWNLOADER|User-Agent=Mozilla/5.0 (iPad; CPU OS 6_0 like Mac OS X) AppleWebKit/536.26 (KHTML, like Gecko) Version/6.0 Mobile/10A5376e Safari/8536.25</link>
<thumbnail>http://i.imgur.com/EuQiOf1.png</thumbnail>
</item>
DISNEY CHANNEL
<item>
<title></title>
<link></link>
<thumbnail></thumbnail>
</item>
DISNEY JUNIOR
<item>
<title>[B][COLOR lawngreen]•[/B][/COLOR] PT: [B][COLOR white]DISNEY JUNIOR[B][COLOR royalblue] [SD] [B][COLOR red](f4mTester)[/B][/COLOR]</title>
<link>plugin://plugin.video.f4mTester/?url=http://worldcs.info:8080/live/SUsojOyxUv/LR16au3pFJ/689.ts;streamtype=TSDOWNLOADER|User-Agent=Mozilla/5.0 (iPad; CPU OS 6_0 like Mac OS X) AppleWebKit/536.26 (KHTML, like Gecko) Version/6.0 Mobile/10A5376e Safari/8536.25</link>
<thumbnail>http://i.imgur.com/CZvsFYH.png</thumbnail>
</item>
JIM JAM
<item>
<title>[B][COLOR lawngreen]•[/B][/COLOR] PT: [B][COLOR white]JIM JAM[B][COLOR royalblue] [SD] [B][COLOR red](f4mTester)[/B][/COLOR]</title>
<link>plugin://plugin.video.f4mTester/?url=http://hyper.de1-eu.com:8000/live/aria/aria/2804.ts;streamtype=TSDOWNLOADER|User-Agent=Mozilla/5.0 (iPad; CPU OS 6_0 like Mac OS X) AppleWebKit/536.26 (KHTML, like Gecko) Version/6.0 Mobile/10A5376e Safari/8536.25</link>
<thumbnail>http://i.imgur.com/b6Mhyk9.png</thumbnail>
</item>
NICKELODEON
<item>
<title>[B][COLOR lawngreen]•[/B][/COLOR] PT: [B][COLOR white]NICKELODEON[B][COLOR royalblue] [SD] [B][COLOR red](f4mTester)[/B][/COLOR]</title>
<link>plugin://plugin.video.f4mTester/?url=http://globiptv.com:8000/live/W9yYsrqm4o/5923D2605/2074.ts;streamtype=TSDOWNLOADER|User-Agent=Mozilla/5.0 (iPad; CPU OS 6_0 like Mac OS X) AppleWebKit/536.26 (KHTML, like Gecko) Version/6.0 Mobile/10A5376e Safari/8536.25</link>
<thumbnail>http://i.imgur.com/8fMIHmp.png</thumbnail>
</item>
PANDA BIGGS
<item>
<title>[B][COLOR lawngreen]•[/B][/COLOR] PT: [B][COLOR white]PANDA BIGGS[B][COLOR royalblue] [SD] [B][COLOR red](f4mTester)[/B][/COLOR]</title>
<link>plugin://plugin.video.f4mTester/?url=http://globiptv.com:8000/live/W9yYsrqm4o/5923D2605/2073.ts;streamtype=TSDOWNLOADER|User-Agent=Mozilla/5.0 (iPad; CPU OS 6_0 like Mac OS X) AppleWebKit/536.26 (KHTML, like Gecko) Version/6.0 Mobile/10A5376e Safari/8536.25</link>
<thumbnail>http://i.imgur.com/HKbRVtU.png</thumbnail>
</item>
SIC K
<item>
<title>[B][COLOR lawngreen]•[/B][/COLOR] PT: [B][COLOR white]SIC K[B][COLOR royalblue] [SD] [B][COLOR red](f4mTester)[/B][/COLOR]</title>
<link>plugin://plugin.video.f4mTester/?url=http://iptv.iptvthebest.net:15000/live/supertes79@gmail.com/v312d8IqOe/4004.ts;streamtype=TSDOWNLOADER|User-Agent=Mozilla/5.0 (iPad; CPU OS 6_0 like Mac OS X) AppleWebKit/536.26 (KHTML, like Gecko) Version/6.0 Mobile/10A5376e Safari/8536.25</link>
<thumbnail>http://i.imgur.com/lhej3uE.png</thumbnail>
</item>
