<item>
<title>[B][COLOR yellow]ATUALIZACAO: 26.05.2016[/B][/COLOR]</title>
<link>http://0.0.0.0:1234</link>
<thumbnail></thumbnail>
</item>
<item>
<title>[B][COLOR white]--------------------------------------------------[/B][/COLOR]</title>
<link>http://0.0.0.0:1234</link>
<thumbnail></thumbnail>
</item>
**************************************************
RTP 1
<item>
<title>lawngreen] PT: [B][COLOR white][B][COLOR [B][COLOR royalblue] [SD 576p] [B][COLOR red](http://5.39.66.183:8000/live/bruno/bruno/16.ts)[/B][/COLOR]</title>
<link>plugin://plugin.video.f4mTester/?url=http://5.39.66.183:8000/live/bruno/bruno/16.ts;streamtype=TSDOWNLOADER|User-Agent=Mozilla/5.0 (iPad; CPU OS 6_0 like Mac OS X) AppleWebKit/536.26 (KHTML, like Gecko) Version/6.0 Mobile/10A5376e Safari/8536.25</link>
<thumbnail>http://i.imgur.com/pjjlbCF.png</thumbnail>
</item>
RTP 2
<item>
<title>[B][COLOR lawngreen]•[/B][/COLOR] PT: [B][COLOR white]RTP 2[B][COLOR royalblue] [SD 360p] [B][COLOR red](f4mTester)[/B][/COLOR]</title>
<link>plugin://plugin.video.f4mTester/?url=http://ipsatpro.com:8000/live/Giovanni/xSq7wb3dB6/894.ts;streamtype=TSDOWNLOADER|User-Agent=Mozilla/5.0 (iPad; CPU OS 6_0 like Mac OS X) AppleWebKit/536.26 (KHTML, like Gecko) Version/6.0 Mobile/10A5376e Safari/8536.25</link>
<thumbnail>http://i.imgur.com/krvWl4X.png</thumbnail>
</item>
RTP 3
<item>
<title>[B][COLOR lawngreen]•[/B][/COLOR] PT: [B][COLOR white]RTP 3[B][COLOR royalblue] [SD 576p] [B][COLOR red](f4mTester)[/B][/COLOR]</title>
<link>plugin://plugin.video.f4mTester/?url=http://5.39.66.183:8000/live/bruno/bruno/12.ts;streamtype=TSDOWNLOADER|User-Agent=Mozilla/5.0 (iPad; CPU OS 6_0 like Mac OS X) AppleWebKit/536.26 (KHTML, like Gecko) Version/6.0 Mobile/10A5376e Safari/8536.25</link>
<thumbnail>http://i.imgur.com/mrqnruN.png</thumbnail>
</item>
RTP ACORES
<item>
<title>[B][COLOR lawngreen]•[/B][/COLOR] PT: [B][COLOR white]RTP ACORES[B][COLOR royalblue] [SD 360p] [B][COLOR red](f4mTester)[/B][/COLOR]</title>
<link>plugin://plugin.video.f4mTester/?url=http://ipsatpro.com:8000/live/Giovanni/xSq7wb3dB6/893.ts;streamtype=TSDOWNLOADER|User-Agent=Mozilla/5.0 (iPad; CPU OS 6_0 like Mac OS X) AppleWebKit/536.26 (KHTML, like Gecko) Version/6.0 Mobile/10A5376e Safari/8536.25</link>
<thumbnail>http://i.imgur.com/om9BKuk.png</thumbnail>
</item>
RTP AFRICA
<item>
<title>[B][COLOR lawngreen]•[/B][/COLOR] PT: [B][COLOR white]RTP AFRICA[B][COLOR royalblue] [SD 576p] [B][COLOR red](f4mTester)[/B][/COLOR]</title>
<link>plugin://plugin.video.f4mTester/?url=http://5.39.66.183:8000/live/bruno/bruno/531.ts;streamtype=TSDOWNLOADER|User-Agent=Mozilla/5.0 (iPad; CPU OS 6_0 like Mac OS X) AppleWebKit/536.26 (KHTML, like Gecko) Version/6.0 Mobile/10A5376e Safari/8536.25</link>
<thumbnail>http://i.imgur.com/YWi6NzU.png</thumbnail>
</item>
RTP INTERNACIONAL
<item>
<title></title>
<link></link>
<thumbnail></thumbnail>
</item>
RTP MADEIRA
<item>
<title>[B][COLOR lawngreen]•[/B][/COLOR] PT: [B][COLOR white]RTP MADEIRA[B][COLOR royalblue] [SD 360p] [B][COLOR red](f4mTester)[/B][/COLOR]</title>
<link>plugin://plugin.video.f4mTester/?url=http://ipsatpro.com:8000/live/Antonioenzo/Wqvbh99so2/891.ts;streamtype=TSDOWNLOADER|User-Agent=Mozilla/5.0 (iPad; CPU OS 6_0 like Mac OS X) AppleWebKit/536.26 (KHTML, like Gecko) Version/6.0 Mobile/10A5376e Safari/8536.25</link>
<thumbnail>http://i.imgur.com/EQk4X7n.png</thumbnail>
</item>
RTP MEMORIA
<item>
<title>[B][COLOR lawngreen]•[/B][/COLOR] PT: [B][COLOR white]RTP MEMORIA[B][COLOR royalblue] [SD 360p] [B][COLOR red](f4mTester)[/B][/COLOR]</title>
<link>plugin://plugin.video.f4mTester/?url=http://ipsatpro.com:8000/live/Antonioenzo/Wqvbh99so2/890.ts;streamtype=TSDOWNLOADER|User-Agent=Mozilla/5.0 (iPad; CPU OS 6_0 like Mac OS X) AppleWebKit/536.26 (KHTML, like Gecko) Version/6.0 Mobile/10A5376e Safari/8536.25</link>
<thumbnail>http://i.imgur.com/lWlG90R.png</thumbnail>
</item>
SIC
<item>
<title>[B][COLOR lawngreen]•[/B][/COLOR] PT: [B][COLOR white]SIC[B][COLOR royalblue] [SD 576p] [B][COLOR red](f4mTester)[/B][/COLOR]</title>
<link>plugin://plugin.video.f4mTester/?url=http://ipsatpro.com:8000/live/Giovanni/xSq7wb3dB6/924.ts;streamtype=TSDOWNLOADER|User-Agent=Mozilla/5.0 (iPad; CPU OS 6_0 like Mac OS X) AppleWebKit/536.26 (KHTML, like Gecko) Version/6.0 Mobile/10A5376e Safari/8536.25</link>
<thumbnail>http://i.imgur.com/U0XKwI5.png</thumbnail>
</item>
SIC CARAS
<item>
<title></title>
<link></link>
<thumbnail></thumbnail>
</item>
SIC MULHER
<item>
<title>[B][COLOR lawngreen]•[/B][/COLOR] PT: [B][COLOR white]SIC MULHER[B][COLOR royalblue] [SD 576p] [B][COLOR red](f4mTester)[/B][/COLOR]</title>
<link>plugin://plugin.video.f4mTester/?url=http://ipsatpro.com:8000/live/Giovanni/xSq7wb3dB6/913.ts;streamtype=TSDOWNLOADER|User-Agent=Mozilla/5.0 (iPad; CPU OS 6_0 like Mac OS X) AppleWebKit/536.26 (KHTML, like Gecko) Version/6.0 Mobile/10A5376e Safari/8536.25</link>
<thumbnail>http://i.imgur.com/PM9mIG3.png</thumbnail>
</item>
SIC NOTICIAS
<item>
<title>[B][COLOR lawngreen]•[/B][/COLOR] PT: [B][COLOR white]SIC NOTICIAS[B][COLOR royalblue] [SD 576p] [B][COLOR red](f4mTester)[/B][/COLOR]</title>
<link>plugin://plugin.video.f4mTester/?url=http://ipsatpro.com:8000/live/Antonioenzo/Wqvbh99so2/903.ts;streamtype=TSDOWNLOADER|User-Agent=Mozilla/5.0 (iPad; CPU OS 6_0 like Mac OS X) AppleWebKit/536.26 (KHTML, like Gecko) Version/6.0 Mobile/10A5376e Safari/8536.25</link>
<thumbnail>http://i.imgur.com/qdQ02xS.png</thumbnail>
</item>
SIC RADICAL
<item>
<title>[B][COLOR lawngreen]•[/B][/COLOR] PT: [B][COLOR white]SIC RADICAL[B][COLOR royalblue] [SD 576p] [B][COLOR red](f4mTester)[/B][/COLOR]</title>
<link>plugin://plugin.video.f4mTester/?url=http://ipsatpro.com:8000/live/Giovanni/xSq7wb3dB6/914.ts;streamtype=TSDOWNLOADER|User-Agent=Mozilla/5.0 (iPad; CPU OS 6_0 like Mac OS X) AppleWebKit/536.26 (KHTML, like Gecko) Version/6.0 Mobile/10A5376e Safari/8536.25</link>
<thumbnail>http://i.imgur.com/Vvv2OcG.png</thumbnail>
</item>
TVI
<item>
<title>[B][COLOR lawngreen]•[/B][/COLOR] PT: [B][COLOR white]TVI[B][COLOR royalblue] [SD 576p] [B][COLOR red](f4mTester)[/B][/COLOR]</title>
<link>plugin://plugin.video.f4mTester/?url=http://ipsatpro.com:8000/live/Antonioenzo/Wqvbh99so2/889.ts;streamtype=TSDOWNLOADER|User-Agent=Mozilla/5.0 (iPad; CPU OS 6_0 like Mac OS X) AppleWebKit/536.26 (KHTML, like Gecko) Version/6.0 Mobile/10A5376e Safari/8536.25</link>
<thumbnail>http://i.imgur.com/eoUkAQT.png</thumbnail>
</item>
TVI 24
<item>
<title>[B][COLOR lawngreen]•[/B][/COLOR] PT: [B][COLOR white]TVI 24[B][COLOR royalblue] [SD 576p] [B][COLOR red](f4mTester)[/B][/COLOR]</title>
<link>plugin://plugin.video.f4mTester/?url=http://5.39.66.183:8000/live/bruno/bruno/17.ts;streamtype=TSDOWNLOADER|User-Agent=Mozilla/5.0 (iPad; CPU OS 6_0 like Mac OS X) AppleWebKit/536.26 (KHTML, like Gecko) Version/6.0 Mobile/10A5376e Safari/8536.25</link>
<thumbnail>http://i.imgur.com/nYX9hTR.png</thumbnail>
</item>
TVI FICCAO
<item>
<title>[B][COLOR lawngreen]•[/B][/COLOR] PT: [B][COLOR white]TVI FICCAO[B][COLOR royalblue] [SD 576p] [B][COLOR red](f4mTester)[/B][/COLOR]</title>
<link>plugin://plugin.video.f4mTester/?url=http://ipsatpro.com:8000/live/Antonioenzo/Wqvbh99so2/886.ts;streamtype=TSDOWNLOADER|User-Agent=Mozilla/5.0 (iPad; CPU OS 6_0 like Mac OS X) AppleWebKit/536.26 (KHTML, like Gecko) Version/6.0 Mobile/10A5376e Safari/8536.25</link>
<thumbnail>http://i.imgur.com/1OKBioL.png</thumbnail>
</item>
+TVI
<item>
<title>[B][COLOR lawngreen]•[/B][/COLOR] PT: [B][COLOR white]+TVI[B][COLOR royalblue] [SD 576p] [B][COLOR red](f4mTester)[/B][/COLOR]</title>
<link>plugin://plugin.video.f4mTester/?url=http://ipsatpro.com:8000/live/Giovanni/xSq7wb3dB6/887.ts;streamtype=TSDOWNLOADER|User-Agent=Mozilla/5.0 (iPad; CPU OS 6_0 like Mac OS X) AppleWebKit/536.26 (KHTML, like Gecko) Version/6.0 Mobile/10A5376e Safari/8536.25</link>
<thumbnail>http://i.imgur.com/XZBNbmj.png</thumbnail>
</item>
TVI REALITY
<item>
<title>[B][COLOR lawngreen]•[/B][/COLOR] PT: [B][COLOR white]TVI REALITY[B][COLOR royalblue] [SD 360p] [B][COLOR red](f4mTester)[/B][/COLOR]</title>
<link>plugin://plugin.video.f4mTester/?url=http://5.39.66.183:8000/live/bruno/bruno/1875.ts;streamtype=TSDOWNLOADER|User-Agent=Mozilla/5.0 (iPad; CPU OS 6_0 like Mac OS X) AppleWebKit/536.26 (KHTML, like Gecko) Version/6.0 Mobile/10A5376e Safari/8536.25</link>
<thumbnail>http://i.imgur.com/D9HZ95f.png</thumbnail>
</item>
PORTO CANAL
<item>
<title>[B][COLOR lawngreen]•[/B][/COLOR] PT: [B][COLOR white]PORTO CANAL[B][COLOR royalblue] [SD 576p] [B][COLOR red](f4mTester)[/B][/COLOR]</title>
<link>plugin://plugin.video.f4mTester/?url=http://ipsatpro.com:8000/live/Giovanni/xSq7wb3dB6/919.ts;streamtype=TSDOWNLOADER|User-Agent=Mozilla/5.0 (iPad; CPU OS 6_0 like Mac OS X) AppleWebKit/536.26 (KHTML, like Gecko) Version/6.0 Mobile/10A5376e Safari/8536.25</link>
<thumbnail>http://i.imgur.com/6Ojn6Et.png</thumbnail>
</item>
A BOLA TV
<item>
<title>[B][COLOR lawngreen]•[/B][/COLOR] PT: [B][COLOR white]A BOLA TV[B][COLOR royalblue] [SD 576p] [B][COLOR red](f4mTester)[/B][/COLOR]</title>
<link>plugin://plugin.video.f4mTester/?url=http://ipsatpro.com:8000/live/Antonioenzo/Wqvbh99so2/910.ts´~;streamtype=TSDOWNLOADER|User-Agent=Mozilla/5.0 (iPad; CPU OS 6_0 like Mac OS X) AppleWebKit/536.26 (KHTML, like Gecko) Version/6.0 Mobile/10A5376e Safari/8536.25</link>
<thumbnail>http://i.imgur.com/aDTQAYr.png</thumbnail>
</item>
CMTV
<item>
<title>[B][COLOR lawngreen]•[/B][/COLOR] PT: [B][COLOR white]CMTV[B][COLOR royalblue] [SD 576p] [B][COLOR red](f4mTester)[/B][/COLOR]</title>
<link>plugin://plugin.video.f4mTester/?url=http://ipsatpro.com:8000/live/Antonioenzo/Wqvbh99so2/908.ts;streamtype=TSDOWNLOADER|User-Agent=Mozilla/5.0 (iPad; CPU OS 6_0 like Mac OS X) AppleWebKit/536.26 (KHTML, like Gecko) Version/6.0 Mobile/10A5376e Safari/8536.25</link>
<thumbnail>http://www.thelogodb.com/images/media/logo/uvqwuu1436843714.png</thumbnail>
</item>
SPORTING TV
<item>
<title>[B][COLOR lawngreen]•[/B][/COLOR] PT: [B][COLOR white]SPORTING TV[B][COLOR royalblue] [SD 576p] [B][COLOR red](f4mTester)[/B][/COLOR]</title>
<link>plugin://plugin.video.f4mTester/?url=http://boxiptv.noip.us:9998/live/ourartou/ourartou/1028.ts;streamtype=TSDOWNLOADER|User-Agent=Mozilla/5.0 (iPad; CPU OS 6_0 like Mac OS X) AppleWebKit/536.26 (KHTML, like Gecko) Version/6.0 Mobile/10A5376e Safari/8536.25</link>
<thumbnail>http://i.imgur.com/KTEBwY0.png</thumbnail>
</item>
TV GLOBO
<item>
<title>lawngreen]•[/B][/COLOR] PT: [B][COLOR white]TV GLOBO[B][COLOR royalblue] [SD 404p] [B][COLOR red](f4mTester)[/B][/COLOR]</title>
<link>plugin://plugin.video.f4mTester/?url=http://ipsatpro.com:8000/live/Giovanni/xSq7wb3dB6/888.ts;streamtype=TSDOWNLOADER|User-Agent=Mozilla/5.0 (iPad; CPU OS 6_0 like Mac OS X) AppleWebKit/536.26 (KHTML, like Gecko) Version/6.0 Mobile/10A5376e Safari/8536.25</link>
<thumbnail>http://i.imgur.com/1OKBioL.png</thumbnail>
</item>
TV GLOBO PREMIUM
<item>
<title>lawngreen]•[/B][/COLOR] PT: [B][COLOR white]TV GLOBO PREMIUM[B][COLOR royalblue] [SD 576p] [B][COLOR red](f4mTester)[/B][/COLOR]</title>
<link>plugin://plugin.video.f4mTester/?url=http://ipsatpro.com:8000/live/Giovanni/xSq7wb3dB6/931.ts;streamtype=TSDOWNLOADER|User-Agent=Mozilla/5.0 (iPad; CPU OS 6_0 like Mac OS X) AppleWebKit/536.26 (KHTML, like Gecko) Version/6.0 Mobile/10A5376e Safari/8536.25</link>
<thumbnail>http://i.imgur.com/1OKBioL.png</thumbnail>
</item>
TV RECORD
<item>
<title>lawngreen]•[/B][/COLOR] PT: [B][COLOR white]TV RECORD[B][COLOR royalblue] [SD 576p] [B][COLOR red](f4mTester)[/B][/COLOR]</title>
<link>plugin://plugin.video.f4mTester/?url=http://ipsatpro.com:8000/live/Antonioenzo/Wqvbh99so2/917.ts;streamtype=TSDOWNLOADER|User-Agent=Mozilla/5.0 (iPad; CPU OS 6_0 like Mac OS X) AppleWebKit/536.26 (KHTML, like Gecko) Version/6.0 Mobile/10A5376e Safari/8536.25</link>
<thumbnail>http://i.imgur.com/1OKBioL.png</thumbnail>
</item>
TV RECORD NEWS
<item>
<title></title>
<link></link>
<thumbnail></thumbnail>
</item>
